Lab4/decoder.v
// mips_decode: a decoder for MIPS arithmetic instructions
//
// rd_src      (output) - should the destination register be rd (0) or rt (1)
// writeenable (output) - should a new value be captured by the register file
// alu_src2    (output) - should the 2nd ALU source be a register (0), zero extended immediate or sign extended immediate
// alu_op      (output) - control signal to be sent to the ALU
// except      (output) - set to 1 when the opcode/funct combination is unrecognized
// opcode      (input)  - the opcode field from the instruction
// funct       (input)  - the function field from the instruction
//

module mips_decode(rd_src, writeenable, alu_src2, alu_op, except, opcode, funct);
    output       rd_src, writeenable, except;
    output [1:0] alu_src2;
    output [2:0] alu_op;
    input  [5:0] opcode, funct;

    
    wire w_op0 = opcode == `OP_OTHER0;

    //regular
    wire w_add = w_op0 & (funct == `OP0_ADD);
    wire w_sub = w_op0 & (funct == `OP0_SUB);
    wire w_and = w_op0 & (funct == `OP0_AND);
    wire w_or = w_op0 & (funct == `OP0_OR);
    wire w_nor = w_op0 & (funct == `OP0_NOR);
    wire w_xor = w_op0 & (funct == `OP0_XOR);

    //immediate
    wire w_addi = (opcode == `OP_ADDI);
    wire w_andi = (opcode == `OP_ANDI);
    wire w_ori = (opcode == `OP_ORI);
    wire w_xori = (opcode == `OP_XORI);

    assign alu_op[0] = (w_sub | w_or | w_xor | w_ori | w_xori);
    assign alu_op[1] = (w_add | w_sub | w_xor | w_nor | w_addi | w_xori);
    assign alu_op[2] = (w_and | w_or | w_nor | w_xor | w_xori | w_andi | w_ori);

    nor nr1(except, w_add , w_sub , w_and , w_or , w_nor , w_xor , w_addi , w_andi , w_ori , w_xori);
    assign alu_src2[1] =  w_andi | w_ori | w_xori;
    assign alu_src2[0] = w_addi;
    assign rd_src = w_andi | w_addi | w_ori | w_xori;
    wire writeenable = ~except;



    


endmodule // mips_decode

Lab4/decoder_tb.v
module decoder_test;
    reg [5:0] opcode, funct;

    initial begin
        $dumpfile("decoder.vcd");
        $dumpvars(0, decoder_test);

             opcode = `OP_OTHER0; funct = `OP0_ADD; // try addition
        # 10 opcode = `OP_OTHER0; funct = `OP0_SUB; // try subtraction
        # 10 opcode = `OP_OTHER0; funct = `OP0_OR; // try or
        # 10 opcode = `OP_OTHER0; funct = `OP0_XOR; // try xor
        # 10 opcode = `OP_OTHER0; funct = `OP0_NOR; // try nor
        //immediates
        # 10 opcode = `OP_ADDI; 
        # 10 opcode = `OP_ANDI;
        # 10 opcode = `OP_ORI;
        # 10 opcode = `OP_XORI;
        # 10 opcode = 6'b101010; funct = `OP0_ADD;
        # 10 opcode = 6'b110111; funct = `OP0_SUB;
        # 10 opcode = 6'b110111; funct = `OP0_AND;

        # 10 $finish;
    end

    // use gtkwave to test correctness
    wire [2:0] alu_op;
    wire [1:0] alu_src2; 
    wire       rd_src, writeenable, except;
    mips_decode decoder(rd_src, writeenable, alu_src2, alu_op, except,
                        opcode, funct);
endmodule // decoder_test

Lab4/decoder.vcd
$date
	Sat Feb 20 15:36:30 2021
$end
$version
	Icarus Verilog
$end
$timescale
	1s
$end
$scope module decoder_test $end
$var wire 1 ! writeenable $end
$var wire 1 " rd_src $end
$var wire 1 # except $end
$var wire 2 $ alu_src2 [1:0] $end
$var wire 3 % alu_op [2:0] $end
$var reg 6 & funct [5:0] $end
$var reg 6 ' opcode [5:0] $end
$scope module decoder $end
$var wire 1 # except $end
$var wire 6 ( funct [5:0] $end
$var wire 6 ) opcode [5:0] $end
$var wire 1 " rd_src $end
$var wire 1 * w_add $end
$var wire 1 + w_and $end
$var wire 1 , w_nor $end
$var wire 1 - w_or $end
$var wire 1 . w_sub $end
$var wire 1 / w_xor $end
$var wire 1 ! writeenable $end
$var wire 1 0 w_xori $end
$var wire 1 1 w_ori $end
$var wire 1 2 w_op0 $end
$var wire 1 3 w_andi $end
$var wire 1 4 w_addi $end
$var wire 2 5 alu_src2 [1:0] $end
$var wire 3 6 alu_op [2:0] $end
$upscope $end
$upscope $end
$enddefinitions $end
#0
$dumpvars
b10 6
b0 5
04
03
12
01
00
0/
0.
0-
0,
0+
1*
b0 )
b100000 (
b0 '
b100000 &
b10 %
b0 $
0#
0"
1!
$end
#10
b11 %
b11 6
0*
1.
b100010 &
b100010 (
#20
b101 %
b101 6
0.
1-
b100101 &
b100101 (
#30
b111 %
b111 6
0-
1/
b100110 &
b100110 (
#40
b110 %
b110 6
1,
0/
b100111 &
b100111 (
#50
b10 %
b10 6
1"
0,
02
b1 $
b1 5
14
b1000 '
b1000 )
#60
b100 %
b100 6
b10 $
b10 5
04
13
b1100 '
b1100 )
#70
b101 %
b101 6
03
11
b1101 '
b1101 )
#80
b111 %
b111 6
01
10
b1110 '
b1110 )
#90
0!
1#
0"
b0 $
b0 5
b0 %
b0 6
b100000 &
b100000 (
00
b101010 '
b101010 )
#100
b100010 &
b100010 (
b110111 '
b110111 )
#110
b100100 &
b100100 (
