Lab3/register.v
// register: A register which may be reset to an arbirary value
//
// q      (output) - Current value of register
// d      (input)  - Next value of register
// clk    (input)  - Clock (positive edge-sensitive)
// enable (input)  - Load new value? (yes = 1, no = 0)
// reset  (input)  - Asynchronous reset    (reset = 1)
//
module register(q, d, clk, enable, reset);

    output [31:0] q;
    input  [31:0] d;
    input  clk, enable, reset;

   //  Your implementation goes here
  dffe df1(q[0], d[0], clk, enable, reset);
  dffe df2(q[1], d[1], clk, enable, reset);
  dffe df3(q[2], d[2], clk, enable, reset);
  dffe df4(q[3], d[3], clk, enable, reset);
  dffe df5(q[4], d[4], clk, enable, reset);
  dffe df6(q[5], d[5], clk, enable, reset);
  dffe df7(q[6], d[6], clk, enable, reset);
  dffe df8(q[7], d[7], clk, enable, reset);
  dffe df9(q[8], d[8], clk, enable, reset);
  dffe df10(q[9], d[9], clk, enable, reset);
  dffe df11(q[10], d[10], clk, enable, reset);
  dffe df12(q[11], d[11], clk, enable, reset);
  dffe df13(q[12], d[12], clk, enable, reset);
  dffe df14(q[13], d[13], clk, enable, reset);
  dffe df15(q[14], d[14], clk, enable, reset);
  dffe df16(q[15], d[15], clk, enable, reset);
  dffe df17(q[16], d[16], clk, enable, reset);
  dffe df18(q[17], d[17], clk, enable, reset);
  dffe df19(q[18], d[18], clk, enable, reset);
  dffe df20(q[19], d[19], clk, enable, reset);
  dffe df21(q[20], d[20], clk, enable, reset);
  dffe df22(q[21], d[21], clk, enable, reset);
  dffe df23(q[22], d[22], clk, enable, reset);
  dffe df24(q[23], d[23], clk, enable, reset);
  dffe df25(q[24], d[24], clk, enable, reset);
  dffe df26(q[25], d[25], clk, enable, reset);
  dffe df27(q[26], d[26], clk, enable, reset);
  dffe df28(q[27], d[27], clk, enable, reset);
  dffe df29(q[28], d[28], clk, enable, reset);
  dffe df30(q[29], d[29], clk, enable, reset);
  dffe df31(q[30], d[30], clk, enable, reset);
  dffe df32(q[31], d[31], clk, enable, reset);



endmodule // register



// dffe: D-type flip-flop with enable
//
// q      (output) - Current value of flip flop
// d      (input)  - Next value of flip flop
// clk    (input)  - Clock (positive edge-sensitive)
// enable (input)  - Load new value? (yes = 1, no = 0)
// reset  (input)  - Asynchronous reset   (reset =  1)
//
module dffe(q, d, clk, enable, reset);
   output q;
   reg    q;
   input  d;
   input  clk, enable, reset;

   always@(reset)
     if (reset == 1'b1)
       q <= 0;

   always@(posedge clk)
     if ((reset == 1'b0) && (enable == 1'b1))
       q <= d;
endmodule // dffe

Lab3/register_tb.v
module test;
    reg       clk = 0, enable = 0, reset = 1;  // start by reseting the register file

    /* Make a regular pulsing clock with a 10 time unit period. */
    always #5 clk = !clk;

    reg [31:0] d;

    wire [31:0] q;
    initial begin
        $dumpfile("register.vcd");
        $dumpvars(0, test);
        # 10  reset = 0;      // stop reseting the register 

        # 10
          // write 88 to the register
          enable = 1;
          d = 88;

        # 10
          // try writing to the register when its disabled
          enable = 0;
          d = 89;

        // Add your own testcases here!
        
        # 10
          enable = 1;
          d = 42;

        # 10
          enable = 1;
          d = 1;

        # 10
          enable = 1;
          d = 1;

        # 10
          enable = 0;
          d = 651;

        # 10
          enable = 0;
          d = 0;



        # 700 $finish;
    end
    
    initial begin
    end

    register reg1(q, d, clk, enable, reset);
   
endmodule // test

Lab3/register.vcd
$date
	Thu Feb 11 12:44:58 2021
$end
$version
	Icarus Verilog
$end
$timescale
	1s
$end
$scope module test $end
$var wire 32 ! q [31:0] $end
$var reg 1 " clk $end
$var reg 32 # d [31:0] $end
$var reg 1 $ enable $end
$var reg 1 % reset $end
$scope module reg1 $end
$var wire 1 " clk $end
$var wire 32 & d [31:0] $end
$var wire 1 $ enable $end
$var wire 1 % reset $end
$var wire 32 ' q [31:0] $end
$scope module df1 $end
$var wire 1 " clk $end
$var wire 1 ( d $end
$var wire 1 $ enable $end
$var wire 1 % reset $end
$var reg 1 ) q $end
$upscope $end
$scope module df10 $end
$var wire 1 " clk $end
$var wire 1 * d $end
$var wire 1 $ enable $end
$var wire 1 % reset $end
$var reg 1 + q $end
$upscope $end
$scope module df11 $end
$var wire 1 " clk $end
$var wire 1 , d $end
$var wire 1 $ enable $end
$var wire 1 % reset $end
$var reg 1 - q $end
$upscope $end
$scope module df12 $end
$var wire 1 " clk $end
$var wire 1 . d $end
$var wire 1 $ enable $end
$var wire 1 % reset $end
$var reg 1 / q $end
$upscope $end
$scope module df13 $end
$var wire 1 " clk $end
$var wire 1 0 d $end
$var wire 1 $ enable $end
$var wire 1 % reset $end
$var reg 1 1 q $end
$upscope $end
$scope module df14 $end
$var wire 1 " clk $end
$var wire 1 2 d $end
$var wire 1 $ enable $end
$var wire 1 % reset $end
$var reg 1 3 q $end
$upscope $end
$scope module df15 $end
$var wire 1 " clk $end
$var wire 1 4 d $end
$var wire 1 $ enable $end
$var wire 1 % reset $end
$var reg 1 5 q $end
$upscope $end
$scope module df16 $end
$var wire 1 " clk $end
$var wire 1 6 d $end
$var wire 1 $ enable $end
$var wire 1 % reset $end
$var reg 1 7 q $end
$upscope $end
$scope module df17 $end
$var wire 1 " clk $end
$var wire 1 8 d $end
$var wire 1 $ enable $end
$var wire 1 % reset $end
$var reg 1 9 q $end
$upscope $end
$scope module df18 $end
$var wire 1 " clk $end
$var wire 1 : d $end
$var wire 1 $ enable $end
$var wire 1 % reset $end
$var reg 1 ; q $end
$upscope $end
$scope module df19 $end
$var wire 1 " clk $end
$var wire 1 < d $end
$var wire 1 $ enable $end
$var wire 1 % reset $end
$var reg 1 = q $end
$upscope $end
$scope module df2 $end
$var wire 1 " clk $end
$var wire 1 > d $end
$var wire 1 $ enable $end
$var wire 1 % reset $end
$var reg 1 ? q $end
$upscope $end
$scope module df20 $end
$var wire 1 " clk $end
$var wire 1 @ d $end
$var wire 1 $ enable $end
$var wire 1 % reset $end
$var reg 1 A q $end
$upscope $end
$scope module df21 $end
$var wire 1 " clk $end
$var wire 1 B d $end
$var wire 1 $ enable $end
$var wire 1 % reset $end
$var reg 1 C q $end
$upscope $end
$scope module df22 $end
$var wire 1 " clk $end
$var wire 1 D d $end
$var wire 1 $ enable $end
$var wire 1 % reset $end
$var reg 1 E q $end
$upscope $end
$scope module df23 $end
$var wire 1 " clk $end
$var wire 1 F d $end
$var wire 1 $ enable $end
$var wire 1 % reset $end
$var reg 1 G q $end
$upscope $end
$scope module df24 $end
$var wire 1 " clk $end
$var wire 1 H d $end
$var wire 1 $ enable $end
$var wire 1 % reset $end
$var reg 1 I q $end
$upscope $end
$scope module df25 $end
$var wire 1 " clk $end
$var wire 1 J d $end
$var wire 1 $ enable $end
$var wire 1 % reset $end
$var reg 1 K q $end
$upscope $end
$scope module df26 $end
$var wire 1 " clk $end
$var wire 1 L d $end
$var wire 1 $ enable $end
$var wire 1 % reset $end
$var reg 1 M q $end
$upscope $end
$scope module df27 $end
$var wire 1 " clk $end
$var wire 1 N d $end
$var wire 1 $ enable $end
$var wire 1 % reset $end
$var reg 1 O q $end
$upscope $end
$scope module df28 $end
$var wire 1 " clk $end
$var wire 1 P d $end
$var wire 1 $ enable $end
$var wire 1 % reset $end
$var reg 1 Q q $end
$upscope $end
$scope module df29 $end
$var wire 1 " clk $end
$var wire 1 R d $end
$var wire 1 $ enable $end
$var wire 1 % reset $end
$var reg 1 S q $end
$upscope $end
$scope module df3 $end
$var wire 1 " clk $end
$var wire 1 T d $end
$var wire 1 $ enable $end
$var wire 1 % reset $end
$var reg 1 U q $end
$upscope $end
$scope module df30 $end
$var wire 1 " clk $end
$var wire 1 V d $end
$var wire 1 $ enable $end
$var wire 1 % reset $end
$var reg 1 W q $end
$upscope $end
$scope module df31 $end
$var wire 1 " clk $end
$var wire 1 X d $end
$var wire 1 $ enable $end
$var wire 1 % reset $end
$var reg 1 Y q $end
$upscope $end
$scope module df32 $end
$var wire 1 " clk $end
$var wire 1 Z d $end
$var wire 1 $ enable $end
$var wire 1 % reset $end
$var reg 1 [ q $end
$upscope $end
$scope module df4 $end
$var wire 1 " clk $end
$var wire 1 \ d $end
$var wire 1 $ enable $end
$var wire 1 % reset $end
$var reg 1 ] q $end
$upscope $end
$scope module df5 $end
$var wire 1 " clk $end
$var wire 1 ^ d $end
$var wire 1 $ enable $end
$var wire 1 % reset $end
$var reg 1 _ q $end
$upscope $end
$scope module df6 $end
$var wire 1 " clk $end
$var wire 1 ` d $end
$var wire 1 $ enable $end
$var wire 1 % reset $end
$var reg 1 a q $end
$upscope $end
$scope module df7 $end
$var wire 1 " clk $end
$var wire 1 b d $end
$var wire 1 $ enable $end
$var wire 1 % reset $end
$var reg 1 c q $end
$upscope $end
$scope module df8 $end
$var wire 1 " clk $end
$var wire 1 d d $end
$var wire 1 $ enable $end
$var wire 1 % reset $end
$var reg 1 e q $end
$upscope $end
$scope module df9 $end
$var wire 1 " clk $end
$var wire 1 f d $end
$var wire 1 $ enable $end
$var wire 1 % reset $end
$var reg 1 g q $end
$upscope $end
$upscope $end
$upscope $end
$enddefinitions $end
#0
$dumpvars
0g
xf
0e
xd
0c
xb
0a
x`
0_
x^
0]
x\
0[
xZ
0Y
xX
0W
xV
0U
xT
0S
xR
0Q
xP
0O
xN
0M
xL
0K
xJ
0I
xH
0G
xF
0E
xD
0C
xB
0A
x@
0?
x>
0=
x<
0;
x:
09
x8
07
x6
05
x4
03
x2
01
x0
0/
x.
0-
x,
0+
x*
0)
x(
b0 '
bx &
1%
0$
bx #
0"
b0 !
$end
#5
1"
#10
0"
0%
#15
1"
#20
0(
0>
0T
1\
1^
0`
1b
0d
0f
0*
0,
0.
00
02
04
06
08
0:
0<
0@
0B
0D
0F
0H
0J
0L
0N
0P
0R
0V
0X
0Z
0"
b1011000 #
b1011000 &
1$
#25
1]
1_
b1011000 !
b1011000 '
1c
1"
#30
1(
0"
b1011001 #
b1011001 &
0$
#35
1"
#40
0(
1>
0^
1`
0b
0"
b101010 #
b101010 &
1$
#45
1?
0_
1a
b101010 !
b101010 '
0c
1"
#50
1(
0>
0\
0`
0"
b1 #
b1 &
#55
0a
0]
0?
b1 !
b1 '
1)
1"
#60
0"
#65
1"
#70
1>
1\
1d
1*
0"
b1010001011 #
b1010001011 &
0$
#75
1"
#80
0(
0>
0\
0d
0*
0"
b0 #
b0 &
